hlpl_transcriber/__init__.py
hlpl_transcriber/__main__.py
hlpl_transcriber/setup.cfg
hlpl_transcriber-1.0.0.dist-info/LICENSE
hlpl_transcriber-1.0.0.dist-info/METADATA
hlpl_transcriber-1.0.0.dist-info/WHEEL
hlpl_transcriber-1.0.0.dist-info/entry_points.txt
hlpl_transcriber-1.0.0.dist-info/top_level.txt
hlpl_transcriber-1.0.0.dist-info/RECORD
