Metadata-Version: 2.1
Name: hlpl-transcriber
Version: 1.0.0
Summary: Text Transcriber
Home-page: https://transcriber.hlpl.net
Author: Ahmida Bendjoudi
Author-email: email@hlpl.net
License: MIT
Download-URL: https://transcriber.hlpl.net/download/
Project-URL: hlpl, https://hlpl.net
Project-URL: hlpl_transcriber-docs, https://docs.hlpl.net
Project-URL: hlpl_transcriber-forum, https://forum.hlpl.net
Project-URL: hlpl_transcriber-resource, https://resource.hlpl.net
Project-URL: hlpl_transcriber-github, https://github.com/hlpl/transcriber
Keywords: hlpl_transcriber,hlpl transcriber,hlpl-transcriber,text transcriber,hlpl
Platform: UNKNOWN
Classifier: Framework :: Robot Framework
Classifier: Framework :: Robot Framework :: Library
Classifier: Framework :: Robot Framework :: Tool
Classifier: Natural Language :: Arabic
Classifier: Natural Language :: English
Requires-Python: >=3, <=3.9
